pdkit/__init__.py
pdkit/clinical_updrs.py
pdkit/finger_tapping_processor.py
pdkit/finger_tapping_time_series.py
pdkit/gait_processor.py
pdkit/gait_time_series.py
pdkit/models.py
pdkit/processor.py
pdkit/qoi_processor.py
pdkit/quicktest_processor.py
pdkit/reaction_processor.py
pdkit/reaction_time_series.py
pdkit/test_result_set.py
pdkit/test_result_set_opdc.py
pdkit/tremor_processor.py
pdkit/tremor_time_series.py
pdkit/updrs.py
pdkit/utils.py
pdkit/voice_processor.py
pdkit-1.4.4.dist-info/LICENSE
pdkit-1.4.4.dist-info/METADATA
pdkit-1.4.4.dist-info/WHEEL
pdkit-1.4.4.dist-info/top_level.txt
pdkit-1.4.4.dist-info/RECORD
