Metadata-Version: 2.1
Name: pdkit
Version: 1.4.4
Summary: The Parkinson`s Disease Data Science Toolkit
Home-page: https://github.com/pdkit/pdkit
Author: PDkit Project members
Author-email: g.roussos@bbk.ac.uk
License: MIT
Keywords: parkinson`s disease
Classifier: Intended Audience :: Developers
Classifier: License :: OSI Approved :: MIT License
Classifier: Natural Language :: English
Classifier: Programming Language :: Python :: 3
Classifier: Programming Language :: Python :: Implementation :: CPython
Classifier: Topic :: Software Development :: Libraries
Classifier: Topic :: Scientific/Engineering :: Bio-Informatics
License-File: LICENSE
